opendea/__init__.py
opendea/_prep.py
opendea/advanced.py
opendea/config.py
opendea/core.py
opendea/dual.py
opendea/exceptions.py
opendea/models.py
opendea/models_pro.py
opendea/plot_theme.py
opendea/plotting.py
opendea/types.py
opendea/utils.py
opendea/version.py
opendea_allys-0.1.1.dist-info/licenses/LICENSE
opendea_allys-0.1.1.dist-info/METADATA
opendea_allys-0.1.1.dist-info/WHEEL
opendea_allys-0.1.1.dist-info/top_level.txt
opendea_allys-0.1.1.dist-info/RECORD
