Metadata-Version: 2.4
Name: opendea-allys
Version: 0.1.1
Summary: Análise Envoltória de Dados (DEA) simples, robusta e extensível em Python.
Author-email: Allyson Aires <allysonaires@gmail.com>
License-Expression: MIT
Project-URL: Homepage, https://github.com/trojanorte/OpenDEA
Project-URL: Issues, https://github.com/trojanorte/OpenDEA
Keywords: DEA,Data Envelopment Analysis,CCR,BCC,eficiência,benchmarking,produtividade
Classifier: Development Status :: 3 - Alpha
Classifier: Intended Audience :: Science/Research
Classifier: Programming Language :: Python :: 3
Classifier: Programming Language :: Python :: 3 :: Only
Classifier: Programming Language :: Python :: 3.9
Classifier: Programming Language :: Python :: 3.10
Classifier: Programming Language :: Python :: 3.11
Classifier: Programming Language :: Python :: 3.12
Classifier: Topic :: Scientific/Engineering
Classifier: Topic :: Scientific/Engineering :: Information Analysis
Requires-Python: >=3.9
License-File: LICENSE
Requires-Dist: numpy<3.0,>=1.24
Requires-Dist: pandas<3.0,>=2.0
Requires-Dist: scipy<2.0,>=1.11
Provides-Extra: viz
Requires-Dist: matplotlib<4.0,>=3.6; extra == "viz"
Requires-Dist: seaborn<0.14,>=0.12; extra == "viz"
Provides-Extra: notebooks
Requires-Dist: jupyter>=1.0; extra == "notebooks"
Requires-Dist: ipykernel>=6.0; extra == "notebooks"
Requires-Dist: ipywidgets>=8.0; extra == "notebooks"
Provides-Extra: dev
Requires-Dist: pytest<9,>=7; extra == "dev"
Requires-Dist: pytest-cov<6,>=4; extra == "dev"
Requires-Dist: ruff<0.7,>=0.5; extra == "dev"
Requires-Dist: black<25.0,>=24.3.0; extra == "dev"
Requires-Dist: build<2.0,>=1.2.1; extra == "dev"
Requires-Dist: twine<6.0,>=5.0.0; extra == "dev"
Provides-Extra: full
Requires-Dist: opendea[dev,notebooks,viz]; extra == "full"
Dynamic: license-file
